qmflows/__init__.py
qmflows/_init_utils.py
qmflows/_logger.py
qmflows/_settings.py
qmflows/_version.py
qmflows/common.py
qmflows/cp2k_utils.py
qmflows/fileFunctions.py
qmflows/py.typed
qmflows/test_utils.py
qmflows/type_hints.py
qmflows/utils.py
qmflows/warnings_qmflows.py
qmflows/yaml_utils.py
qmflows/components/__init__.py
qmflows/components/operations.py
qmflows/components/reactivity.py
qmflows/data/__init__.py
qmflows/data/dictionaries/__init__.py
qmflows/data/dictionaries/generic2ADF.yaml
qmflows/data/dictionaries/generic2CP2K.yaml
qmflows/data/dictionaries/generic2CP2KMM.yaml
qmflows/data/dictionaries/generic2DFTB.yaml
qmflows/data/dictionaries/generic2ORCA.yaml
qmflows/data/dictionaries/generic2PackageWrapper.yaml
qmflows/data/dictionaries/propertiesADF.yaml
qmflows/data/dictionaries/propertiesCP2K.yaml
qmflows/data/dictionaries/propertiesCP2KMM.yaml
qmflows/data/dictionaries/propertiesDFTB.yaml
qmflows/data/dictionaries/propertiesORCA.yaml
qmflows/data/dictionaries/propertiesPackageWrapper.yaml
qmflows/examples/__init__.py
qmflows/examples/Conditional_workflows/__init__.py
qmflows/examples/Conditional_workflows/calc_freqs.py
qmflows/examples/Constrained_and_TS_optimizations/H2O2_TS.py
qmflows/examples/Constrained_and_TS_optimizations/__init__.py
qmflows/examples/Constrained_and_TS_optimizations/generic_constraints.py
qmflows/examples/Constrained_and_TS_optimizations/partial_geometry_opt.py
qmflows/packages/__init__.py
qmflows/packages/_cp2k.py
qmflows/packages/_cp2k_mm.py
qmflows/packages/_orca.py
qmflows/packages/_package_wrapper.py
qmflows/packages/_packages.py
qmflows/packages/_scm.py
qmflows/packages/_serializer.py
qmflows/parsers/__init__.py
qmflows/parsers/_cp2k_basis_parser.py
qmflows/parsers/_cp2k_orbital_parser.py
qmflows/parsers/_generic.py
qmflows/parsers/_xyz.py
qmflows/parsers/adf.py
qmflows/parsers/cp2k.py
qmflows/parsers/orca.py
qmflows/parsers/utils.py
qmflows/templates/__init__.py
qmflows/templates/_templates.py
qmflows-1.0.0.dist-info/LICENSE.md
qmflows-1.0.0.dist-info/METADATA
qmflows-1.0.0.dist-info/WHEEL
qmflows-1.0.0.dist-info/top_level.txt
qmflows-1.0.0.dist-info/RECORD
