Metadata-Version: 2.1
Name: qmflows
Version: 1.0.0
Summary: Automation of computations in quantum chemistry.
Author-email: Felipe Zapata <f.zapata@esciencecenter.nl>
License: QMFlows is an Open Source project supported by the VU University Amsterdam, the Netherlands eScience Center (NLeSC) and Software for Chemistry & Materials BV (SCM, and previously known as Scientific Computing & Modelling NV). The terms of the [LGPL-3.0 license]* apply. As an exception to the LGPL-3.0 license, you agree to grant SCM a [BSD 3-Clause license]** to the contributions you commit on this Github or provide to SCM in another manner.
Project-URL: Homepage, https://github.com/SCM-NV/qmflows
Project-URL: Bug Tracker, https://github.com/SCM-NV/qmflows/issues
Project-URL: Documentation, https://qmflows.readthedocs.io/en/latest/
Keywords: chemistry,workflows,simulation,materials
Classifier: License :: OSI Approved :: GNU Lesser General Public License v3 (LGPLv3)
Classifier: Intended Audience :: Science/Research
Classifier: Programming Language :: Python
Classifier: Programming Language :: Python :: 3
Classifier: Programming Language :: Python :: 3 :: Only
Classifier: Programming Language :: Python :: 3.8
Classifier: Programming Language :: Python :: 3.9
Classifier: Programming Language :: Python :: 3.10
Classifier: Programming Language :: Python :: 3.11
Classifier: Programming Language :: Python :: 3.12
Classifier: Development Status :: 5 - Production/Stable
Classifier: Intended Audience :: Science/Research
Classifier: Topic :: Scientific/Engineering :: Chemistry
Classifier: Typing :: Typed
Requires-Python: >=3.8
License-File: LICENSE.md
Requires-Dist: more-itertools
Requires-Dist: h5py
Requires-Dist: numpy <2,>=1.21
Requires-Dist: pandas
Requires-Dist: noodles >=0.3.3
Requires-Dist: plams ==1.5.1
Requires-Dist: pyparsing !=3.0.0,<3.1.0
Requires-Dist: pyyaml >=5.1
Requires-Dist: filelock
Requires-Dist: packaging >=1.16.8
Provides-Extra: doc
Requires-Dist: sphinx !=3.1.1,<7,>=2.1 ; extra == 'doc'
Requires-Dist: sphinx-autodoc-typehints ; extra == 'doc'
Requires-Dist: sphinx-rtd-theme ; extra == 'doc'
Requires-Dist: nbsphinx ; extra == 'doc'
Requires-Dist: jupyter ; extra == 'doc'
Requires-Dist: pandoc ; extra == 'doc'
Provides-Extra: lint
Requires-Dist: flake8 ; extra == 'lint'
Requires-Dist: pydocstyle[toml] >=6.1 ; extra == 'lint'
Requires-Dist: Flake8-pyproject >=1.2.2 ; extra == 'lint'
Requires-Dist: mypy ; extra == 'lint'
Requires-Dist: types-PyYAML ; extra == 'lint'
Requires-Dist: types-setuptools ; extra == 'lint'
Requires-Dist: pytest >=6.0 ; extra == 'lint'
Provides-Extra: test
Requires-Dist: qmflows[test-no-optional] ; extra == 'test'
Requires-Dist: rdkit >=2018.03.1 ; extra == 'test'
Provides-Extra: test-no-optional
Requires-Dist: assertionlib >=3.1.0 ; extra == 'test-no-optional'
Requires-Dist: pytest >=6.0 ; extra == 'test-no-optional'
Requires-Dist: pytest-cov ; extra == 'test-no-optional'
Requires-Dist: pytest-mock ; extra == 'test-no-optional'
Requires-Dist: typing-extensions ; extra == 'test-no-optional'
